setup.py
caimcaim/__init__.py
caimcaim/caimcaim.py
caimcaim.egg-info/PKG-INFO
caimcaim.egg-info/SOURCES.txt
caimcaim.egg-info/dependency_links.txt
caimcaim.egg-info/not-zip-safe
caimcaim.egg-info/requires.txt
caimcaim.egg-info/top_level.txt